sse_pex_interface/__init__.py
sse_pex_interface/binary_model.py
sse_pex_interface/datatypes.py
sse_pex_interface/pex_file.py
sse_pex_interface/py.typed
sse_pex_interface/sections/__init__.py
sse_pex_interface/sections/debug_function.py
sse_pex_interface/sections/debug_info.py
sse_pex_interface/sections/function.py
sse_pex_interface/sections/header.py
sse_pex_interface/sections/instruction.py
sse_pex_interface/sections/named_function.py
sse_pex_interface/sections/object.py
sse_pex_interface/sections/object_data.py
sse_pex_interface/sections/property.py
sse_pex_interface/sections/state.py
sse_pex_interface/sections/user_flag.py
sse_pex_interface/sections/variable.py
sse_pex_interface/sections/variable_data.py
sse_pex_interface/sections/variable_type.py
sse_pex_interface-1.0.0.dist-info/licenses/LICENSE
sse_pex_interface-1.0.0.dist-info/METADATA
sse_pex_interface-1.0.0.dist-info/WHEEL
sse_pex_interface-1.0.0.dist-info/top_level.txt
sse_pex_interface-1.0.0.dist-info/RECORD
