Metadata-Version: 2.4
Name: sse-pex-interface
Version: 1.0.0
Summary: A Python library for reading and writing Skyrim Special Edition Papyrus Script files (.pex).
Author-email: Cutleast <cutleast@gmail.com>
License: MIT License
Project-URL: Homepage, https://github.com/cutleast/sse-pex-interface
Project-URL: Issues, https://github.com/cutleast/sse-pex-interface/issues
Classifier: Programming Language :: Python :: 3
Classifier: Operating System :: OS Independent
Requires-Python: >=3.12
License-File: LICENSE
Requires-Dist: pydantic
Dynamic: license-file
